sacrebleu/__init__.py
sacrebleu/__main__.py
sacrebleu/compat.py
sacrebleu/dataset.py
sacrebleu/py.typed
sacrebleu/sacrebleu.py
sacrebleu/significance.py
sacrebleu/utils.py
sacrebleu/metrics/__init__.py
sacrebleu/metrics/base.py
sacrebleu/metrics/bleu.py
sacrebleu/metrics/chrf.py
sacrebleu/metrics/clseval.py
sacrebleu/metrics/helpers.py
sacrebleu/metrics/lib_ter.py
sacrebleu/metrics/ter.py
sacrebleu/tokenizers/__init__.py
sacrebleu/tokenizers/tokenizer_13a.py
sacrebleu/tokenizers/tokenizer_base.py
sacrebleu/tokenizers/tokenizer_char.py
sacrebleu/tokenizers/tokenizer_intl.py
sacrebleu/tokenizers/tokenizer_ja_mecab.py
sacrebleu/tokenizers/tokenizer_re.py
sacrebleu/tokenizers/tokenizer_ter.py
sacrebleu/tokenizers/tokenizer_zh.py
sacrebleu_macrof-2.0.1.dist-info/LICENSE.txt
sacrebleu_macrof-2.0.1.dist-info/METADATA
sacrebleu_macrof-2.0.1.dist-info/WHEEL
sacrebleu_macrof-2.0.1.dist-info/entry_points.txt
sacrebleu_macrof-2.0.1.dist-info/top_level.txt
sacrebleu_macrof-2.0.1.dist-info/RECORD
